README.md
setup.py
bayesian_network_cl/__init__.py
bayesian_network_cl/bayesian_network_cl.py
bayesian_network_clb.egg-info/PKG-INFO
bayesian_network_clb.egg-info/SOURCES.txt
bayesian_network_clb.egg-info/dependency_links.txt
bayesian_network_clb.egg-info/top_level.txt