Metadata-Version: 2.1
Name: bayesian-network-clb
Version: 0.1
Summary: Bayesian Network...
Home-page: https://github.com/CRLB-sketch/AI_Lab2
Download-URL: https://github.com/CRLB-sketch/AI_Lab2/tarball/0.1
Author: Cris LB
Author-email: cristianlaynezbachez@gmail.com
License: MIT
Keywords: exercise,testing,prototype
